annot_attrs/main.py
annot_attrs-0.1.4.dist-info/LICENSE
annot_attrs-0.1.4.dist-info/METADATA
annot_attrs-0.1.4.dist-info/WHEEL
annot_attrs-0.1.4.dist-info/top_level.txt
annot_attrs-0.1.4.dist-info/RECORD
